LICENSE
pipewine/__init__.py
pipewine/_op_typing.py
pipewine/_register.py
pipewine/bundle.py
pipewine/dataset.py
pipewine/grabber.py
pipewine/item.py
pipewine/reader.py
pipewine/sample.py
pipewine/cli/__init__.py
pipewine/cli/extension.py
pipewine/cli/main.py
pipewine/cli/mappers.py
pipewine/cli/ops.py
pipewine/cli/sinks.py
pipewine/cli/sources.py
pipewine/cli/utils.py
pipewine/cli/workflows.py
pipewine/mappers/__init__.py
pipewine/mappers/base.py
pipewine/mappers/cache.py
pipewine/mappers/compose.py
pipewine/mappers/crypto.py
pipewine/mappers/item_transform.py
pipewine/mappers/key_transform.py
pipewine/operators/__init__.py
pipewine/operators/base.py
pipewine/operators/cache.py
pipewine/operators/functional.py
pipewine/operators/iter.py
pipewine/operators/merge.py
pipewine/operators/rand.py
pipewine/operators/split.py
pipewine/parsers/__init__.py
pipewine/parsers/base.py
pipewine/parsers/image_parser.py
pipewine/parsers/metadata_parser.py
pipewine/parsers/numpy_parser.py
pipewine/parsers/pickle_parser.py
pipewine/sinks/__init__.py
pipewine/sinks/base.py
pipewine/sinks/fs_utils.py
pipewine/sinks/underfolder.py
pipewine/sources/__init__.py
pipewine/sources/base.py
pipewine/sources/images_folder.py
pipewine/sources/underfolder.py
pipewine/workflows/__init__.py
pipewine/workflows/drawing.py
pipewine/workflows/events.py
pipewine/workflows/execution.py
pipewine/workflows/model.py
pipewine/workflows/tracking.py
pipewine-0.2.0.dist-info/METADATA
pipewine-0.2.0.dist-info/WHEEL
pipewine-0.2.0.dist-info/entry_points.txt
pipewine-0.2.0.dist-info/licenses/LICENSE
pipewine-0.2.0.dist-info/RECORD
