Metadata-Version: 2.4
Name: pipewine
Version: 0.2.0
Summary: Data workflow automation
Author-email: Luca Bonfiglioli <luca.bonfiglioli@gmail.com>
Maintainer-email: Luca Bonfiglioli <luca.bonfiglioli@gmail.com>
License-Expression: Unlicense
License-File: LICENSE
Keywords: dataflow,dataset,orchestration,pipeline,workflow
Classifier: Intended Audience :: Developers
Classifier: Intended Audience :: Science/Research
Classifier: License :: OSI Approved :: The Unlicense (Unlicense)
Classifier: Natural Language :: English
Classifier: Operating System :: OS Independent
Classifier: Programming Language :: Python :: 3
Classifier: Programming Language :: Python :: 3.12
Classifier: Topic :: Scientific/Engineering
Classifier: Topic :: Software Development
Requires-Python: >=3.12
Requires-Dist: imageio
Requires-Dist: numpy
Requires-Dist: pyyaml
Requires-Dist: tifffile
Requires-Dist: typer
Provides-Extra: dev
Requires-Dist: black; extra == 'dev'
Requires-Dist: build; extra == 'dev'
Requires-Dist: flake8; extra == 'dev'
Requires-Dist: hatch; extra == 'dev'
Requires-Dist: mypy; extra == 'dev'
Requires-Dist: pydantic; extra == 'dev'
Requires-Dist: pytest; extra == 'dev'
Requires-Dist: pytest-cov; extra == 'dev'
Provides-Extra: docs
Requires-Dist: mkdocs; extra == 'docs'
Requires-Dist: mkdocs-autoapi; extra == 'docs'
Requires-Dist: mkdocs-material; extra == 'docs'
Requires-Dist: mkdocstrings-python; extra == 'docs'
